AUTHORS
ChangeLog
setup.cfg
setup.py
src/simV2_PyObject.cxx
src/simV2_custom.cxx
src/simV2_wrap.cxx
visitsimv2/__init__.py
visitsimv2/simV2.py
visitsimv2.egg-info/PKG-INFO
visitsimv2.egg-info/SOURCES.txt
visitsimv2.egg-info/dependency_links.txt
visitsimv2.egg-info/not-zip-safe
visitsimv2.egg-info/pbr.json
visitsimv2.egg-info/requires.txt
visitsimv2.egg-info/top_level.txt