Metadata-Version: 1.1
Name: visitsimv2
Version: 17.8.6
Summary: Object oriented python interface for VisIt's simV2 insitu visualization.
Home-page: https://github.com/cstatz/visitsimv2
Author: Christoph Statz
Author-email: christoph.statz@tu-dresden.de
License: BSD-3-Clause
Platform: UNKNOWN
Classifier: Development Status :: 3 - Alpha
Classifier: Environment :: Console
Classifier: Intended Audience :: Developers
Classifier: Intended Audience :: Science/Research
Classifier: License :: OSI Approved :: BSD License
Classifier: Operating System :: OS Independent
Classifier: Programming Language :: Python
Classifier: Topic :: Scientific/Engineering :: Mathematics
Classifier: Topic :: Scientific/Engineering :: Physics
Classifier: Natural Language :: English
